slangweb/__init__.py
slangweb/cli.py
slangweb/constants.py
slangweb/py.typed
slangweb/tools.py
slangweb/translator.py
slangweb-0.0.6.dist-info/METADATA
slangweb-0.0.6.dist-info/WHEEL
slangweb-0.0.6.dist-info/entry_points.txt
slangweb-0.0.6.dist-info/licenses/AUTHORS.rst
slangweb-0.0.6.dist-info/licenses/LICENSE
slangweb-0.0.6.dist-info/RECORD
