Metadata-Version: 2.4
Name: slangweb
Version: 0.0.6
Summary: Simple Language Support for Web Development
Project-URL: Homepage, https://github.com/fitoprincipe/slangweb
Author-email: Rodrigo Esteban Principe <fitoprincipe82@gmail.com>
License: MIT
License-File: AUTHORS.rst
License-File: LICENSE
Keywords: Python,language,web
Classifier: Development Status :: 3 - Alpha
Classifier: Intended Audience :: Developers
Classifier: License :: OSI Approved :: MIT License
Classifier: Programming Language :: Python :: 3.10
Classifier: Programming Language :: Python :: 3.11
Requires-Python: >=3.10
Requires-Dist: deprecated>=1.2.14
Requires-Dist: protobuf
Requires-Dist: sacremoses
Requires-Dist: sentencepiece
Requires-Dist: torch
Requires-Dist: transformers
Provides-Extra: dash
Requires-Dist: dash>=2.0; extra == 'dash'
Provides-Extra: doc
Requires-Dist: pydata-sphinx-theme; extra == 'doc'
Requires-Dist: sphinx-autoapi; extra == 'doc'
Requires-Dist: sphinx-copybutton; extra == 'doc'
Requires-Dist: sphinx-design; extra == 'doc'
Requires-Dist: sphinx>=6.2.1; extra == 'doc'
Provides-Extra: flask
Requires-Dist: flask>=2.0; extra == 'flask'
Provides-Extra: test
Requires-Dist: pytest; extra == 'test'
Requires-Dist: pytest-cov; extra == 'test'
Requires-Dist: pytest-deadfixtures; extra == 'test'
